jarbin_toolkit/__init__.py
jarbin_toolkit-0.1.0.dist-info/licenses/LICENSE
jarbin_toolkit-0.1.0.dist-info/METADATA
jarbin_toolkit-0.1.0.dist-info/WHEEL
jarbin_toolkit-0.1.0.dist-info/top_level.txt
jarbin_toolkit-0.1.0.dist-info/RECORD
