Metadata-Version: 2.4
Name: jarbin-toolkit
Version: 0.1.0
Summary: Tools by Jarjarbin06 (Action / Config / Console / Error / Log / Time)
Author-email: Nathan Jarjarbin <nathan.amaraggi@epitech.eu>
License-Expression: GPL-3.0-or-later
Project-URL: Homepage, https://jarjarbin06.github.io/jarbin-toolkit/
Project-URL: Repository, https://github.com/Jarjarbin06/jarbin-toolkit/
Project-URL: Issues, https://github.com/Jarjarbin06/jarbin-toolkit/issues/
Classifier: Programming Language :: Python :: 3.13
Classifier: Operating System :: OS Independent
Classifier: Environment :: Console
Classifier: Development Status :: 3 - Alpha
Classifier: Intended Audience :: Developers
Classifier: Topic :: Software Development :: Libraries
Classifier: Topic :: Terminals
Classifier: Topic :: Utilities
Requires-Python: >=3.11
License-File: LICENSE
Requires-Dist: jarbin-toolkit-action
Requires-Dist: jarbin-toolkit-config
Requires-Dist: jarbin-toolkit-error
Requires-Dist: jarbin-toolkit-log
Requires-Dist: jarbin-toolkit-time
Requires-Dist: jarbin-toolkit-console
Dynamic: license-file
